huaweicloudsdkgeip/__init__.py
huaweicloudsdkgeip/v3/__init__.py
huaweicloudsdkgeip/v3/geip_async_client.py
huaweicloudsdkgeip/v3/geip_client.py
huaweicloudsdkgeip/v3/model/__init__.py
huaweicloudsdkgeip/v3/model/add_geip_segment_tags_request.py
huaweicloudsdkgeip/v3/model/add_geip_segment_tags_response.py
huaweicloudsdkgeip/v3/model/add_global_eip_tags_request.py
huaweicloudsdkgeip/v3/model/add_global_eip_tags_response.py
huaweicloudsdkgeip/v3/model/add_internet_bandwidth_tags_request.py
huaweicloudsdkgeip/v3/model/add_internet_bandwidth_tags_response.py
huaweicloudsdkgeip/v3/model/allowed_bandwidth_types.py
huaweicloudsdkgeip/v3/model/associate_geip_segment_instance_request.py
huaweicloudsdkgeip/v3/model/associate_geip_segment_instance_response.py
huaweicloudsdkgeip/v3/model/associate_instance_global_eip_request_body.py
huaweicloudsdkgeip/v3/model/associate_instance_global_eip_request_body_global_eip.py
huaweicloudsdkgeip/v3/model/associate_instance_global_eip_request_body_global_eip_associate_instance_info.py
huaweicloudsdkgeip/v3/model/associate_instance_global_eip_request_body_global_eip_gc_bandwidth_info.py
huaweicloudsdkgeip/v3/model/associate_instance_global_eip_segment_request_body.py
huaweicloudsdkgeip/v3/model/associate_instance_global_eip_segment_request_body_global_eip_segment.py
huaweicloudsdkgeip/v3/model/associate_instance_request.py
huaweicloudsdkgeip/v3/model/associate_instance_response.py
huaweicloudsdkgeip/v3/model/attach_internet_bandwidth.py
huaweicloudsdkgeip/v3/model/attach_internet_bandwidth_global_eip.py
huaweicloudsdkgeip/v3/model/attach_internet_bandwidth_global_eip_request_body.py
huaweicloudsdkgeip/v3/model/attach_internet_bandwidth_global_eip_request_body_global_eip.py
huaweicloudsdkgeip/v3/model/attach_internet_bandwidth_request.py
huaweicloudsdkgeip/v3/model/attach_internet_bandwidth_response.py
huaweicloudsdkgeip/v3/model/batch_attach_geip_segment_internet_bandwidth_request.py
huaweicloudsdkgeip-3.1.184.dist-info/METADATA
huaweicloudsdkgeip-3.1.184.dist-info/WHEEL
huaweicloudsdkgeip-3.1.184.dist-info/licenses/LICENSE
huaweicloudsdkgeip-3.1.184.dist-info/RECORD
